onedriveuploader/__init__.py
onedriveuploader/main.py
onedriveuploader-0.2.1.dist-info/METADATA
onedriveuploader-0.2.1.dist-info/WHEEL
onedriveuploader-0.2.1.dist-info/entry_points.txt
onedriveuploader-0.2.1.dist-info/licenses/LICENSE
onedriveuploader-0.2.1.dist-info/RECORD
