Metadata-Version: 2.4
Name: onedriveuploader
Version: 0.2.1
Summary: A CLI tool to upload files to a user's OneDrive via app-only auth.
License-File: LICENSE
Requires-Python: >=3.11
Requires-Dist: msal>=1.32.3
Requires-Dist: requests>=2.32.4
Requires-Dist: rich>=14.0.0
